alsldlawef/README.md
alsldlawef/__init__.py
alsldlawef-0.1.1.dist-info/LICENSE
alsldlawef-0.1.1.dist-info/WHEEL
alsldlawef-0.1.1.dist-info/METADATA
alsldlawef-0.1.1.dist-info/RECORD
