Metadata-Version: 2.1
Name: alsldlawef
Version: 0.1.1
Summary: Let's find some podcasts!
Author-email: Matt Hutchings <HutchingsM1@cardiff.ac.uk>
Classifier: License :: OSI Approved :: MIT License
